arcticrepository/__init__.py
arcticrepository-0.11.dist-info/LICENSE
arcticrepository-0.11.dist-info/METADATA
arcticrepository-0.11.dist-info/WHEEL
arcticrepository-0.11.dist-info/top_level.txt
arcticrepository-0.11.dist-info/RECORD
