Metadata-Version: 2.1
Name: arcticrepository
Version: 0.11
Summary: Wrapper of the Arctic library that includes ElasticSearch indexing
Home-page: UNKNOWN
Author: Tim Watson, Jamie Wooltorton, Henry Jolliffe, Ryszard Dudek, Clare Ford
Author-email: tswatson123@gmail.com
License: MIT
Platform: UNKNOWN
Requires-Dist: arctic (==1.68.0)
Requires-Dist: pandas (==0.23.4)
Requires-Dist: requests
